difflearn/__init__.py
difflearn/models.py
difflearn/simulation.py
difflearn/utils.py
difflearn/visualization.py
difflearn-1.0.4.dist-info/LICENSE.txt
difflearn-1.0.4.dist-info/METADATA
difflearn-1.0.4.dist-info/WHEEL
difflearn-1.0.4.dist-info/top_level.txt
difflearn-1.0.4.dist-info/RECORD
