Metadata-Version: 2.1
Name: difflearn
Version: 1.0.4
Summary: Some useful tools for differential network inference with python.
Home-page: UNKNOWN
Author: Jiacheng Leng
Author-email: jcleng@amss.ac.cn
License: LICENSE.txt
Platform: UNKNOWN
Requires-Python: >=3.6
Requires-Dist: scikit-learn
Requires-Dist: numpy
Requires-Dist: matplotlib
Requires-Dist: scipy
Requires-Dist: rpy2
Requires-Dist: networkx
Requires-Dist: joblib
Requires-Dist: progressbar2
